{"stats":{"mplusOnly":1224,"momaOnly":14109,"both":199},"artists":[{"name":"Ludwig Mies van der Rohe","mplus":1,"moma":16287,"nat":"German","total":16288},{"name":"Pablo Picasso","mplus":1,"moma":1407,"nat":"Spanish","total":1408},{"name":"Frank Lloyd Wright","mplus":14,"moma":878,"nat":"American","total":892},{"name":"Paul Rudolph","mplus":305,"moma":10,"nat":"American","total":315},{"name":"Henri Cartier-Bresson","mplus":2,"moma":306,"nat":"French","total":308},{"name":"Andy Warhol","mplus":5,"moma":279,"nat":"American","total":284},{"name":"Marcel Duchamp","mplus":47,"moma":223,"nat":"French","total":270},{"name":"Nam June Paik","mplus":100,"moma":110,"nat":"American","total":210},{"name":"R. Buckminster Fuller","mplus":96,"moma":49,"nat":"American","total":145},{"name":"Lawrence Weiner","mplus":1,"moma":133,"nat":"American","total":134},{"name":"Martin Parr","mplus":67,"moma":59,"nat":"British","total":126},{"name":"Eleanor Antin","mplus":2,"moma":112,"nat":"American","total":114},{"name":"Yoko Ono","mplus":7,"moma":93,"nat":"Japanese","total":100},{"name":"Mieko Shiomi","mplus":6,"moma":89,"nat":"Japanese","total":95},{"name":"Raj Rewal","mplus":43,"moma":49,"nat":"Indian","total":92},{"name":"Dennis Oppenheim","mplus":1,"moma":89,"nat":"American","total":90},{"name":"On Kawara","mplus":1,"moma":83,"nat":"Japanese","total":84},{"name":"Chris Marker","mplus":51,"moma":26,"nat":"French","total":77},{"name":"Hans Bellmer","mplus":1,"moma":73,"nat":"Polish","total":74},{"name":"Takako Saito","mplus":11,"moma":62,"nat":"Japanese","total":73},{"name":"Gaetano Pesce","mplus":53,"moma":19,"nat":"Italian","total":72},{"name":"Martha Rosler","mplus":4,"moma":68,"nat":"American","total":72},{"name":"John Cage","mplus":12,"moma":59,"nat":"American","total":71},{"name":"Bernard Tschumi","mplus":5,"moma":61,"nat":"()","total":66},{"name":"Ai Weiwei","mplus":28,"moma":36,"nat":"Chinese","total":64},{"name":"Isamu Noguchi","mplus":35,"moma":27,"nat":"American","total":62},{"name":"Marina Abramovi\u0107","mplus":5,"moma":54,"nat":"American","total":59},{"name":"Gabriel Orozco","mplus":10,"moma":49,"nat":"Mexican","total":59},{"name":"Dan Graham","mplus":3,"moma":56,"nat":"American","total":59},{"name":"Georges Hugnet","mplus":2,"moma":53,"nat":"French","total":55},{"name":"Walasse Ting","mplus":1,"moma":53,"nat":"American","total":54},{"name":"Ettore Sottsass","mplus":20,"moma":28,"nat":"Italian","total":48},{"name":"Shigeko Kubota","mplus":7,"moma":41,"nat":"Japanese","total":48},{"name":"Harun Farocki","mplus":3,"moma":44,"nat":"German","total":47},{"name":"Gordon Matta-Clark","mplus":2,"moma":45,"nat":"American","total":47},{"name":"Haegue Yang","mplus":23,"moma":22,"nat":"South Korean","total":45},{"name":"Nalini Malani","mplus":26,"moma":16,"nat":"Indian","total":42},{"name":"Steven Holl","mplus":9,"moma":33,"nat":"American","total":42},{"name":"Nick Mauss","mplus":1,"moma":41,"nat":"American","total":42},{"name":"Lucien Herv\u00e9","mplus":28,"moma":14,"nat":"French","total":42},{"name":"Alvar Aalto","mplus":4,"moma":37,"nat":"Finnish","total":41},{"name":"Vik Muniz","mplus":1,"moma":39,"nat":"Brazilian","total":40},{"name":"Rirkrit Tiravanija","mplus":10,"moma":29,"nat":"Thai","total":39},{"name":"Zao Wou-Ki","mplus":12,"moma":25,"nat":"French","total":37},{"name":"Zaha Hadid","mplus":13,"moma":24,"nat":"British","total":37},{"name":"Cang Xin","mplus":1,"moma":35,"nat":"Chinese","total":36},{"name":"David Diao","mplus":28,"moma":6,"nat":"American","total":34},{"name":"Joan Jonas","mplus":4,"moma":29,"nat":"American","total":33},{"name":"Carolee Schneemann","mplus":3,"moma":29,"nat":"American","total":32},{"name":"Mario Bellini","mplus":2,"moma":29,"nat":"Italian","total":31},{"name":"Hella Jongerius","mplus":1,"moma":29,"nat":"Dutch","total":30},{"name":"Mona Hatoum","mplus":1,"moma":29,"nat":"British","total":30},{"name":"Tracey Moffatt","mplus":16,"moma":13,"nat":"Australian","total":29},{"name":"Zheng Guogu","mplus":28,"moma":1,"nat":"Chinese","total":29},{"name":"Thomas Struth","mplus":1,"moma":27,"nat":"German","total":28},{"name":"Kim Beom","mplus":14,"moma":13,"nat":"South Korean","total":27},{"name":"Lebbeus Woods","mplus":6,"moma":21,"nat":"American","total":27},{"name":"Werner Bischof","mplus":20,"moma":5,"nat":"Swiss","total":25},{"name":"Paul Chan","mplus":7,"moma":18,"nat":"American","total":25},{"name":"Tseng Kwong Chi","mplus":21,"moma":4,"nat":"Canadian","total":25},{"name":"Mark Bradford","mplus":1,"moma":23,"nat":"American","total":24},{"name":"Shahzia Sikander","mplus":1,"moma":22,"nat":"American","total":23},{"name":"Marc Riboud","mplus":18,"moma":4,"nat":"French","total":22},{"name":"Charlotte Posenenske","mplus":13,"moma":9,"nat":"German","total":22},{"name":"James Lee Byars","mplus":1,"moma":21,"nat":"American","total":22},{"name":"Bill Viola","mplus":2,"moma":20,"nat":"American","total":22},{"name":"Yayoi Kusama","mplus":2,"moma":19,"nat":"Japanese","total":21},{"name":"Fang Lijun","mplus":7,"moma":14,"nat":"Chinese","total":21},{"name":"Simryn Gill","mplus":16,"moma":4,"nat":"Singaporean","total":20},{"name":"Michael Graves","mplus":1,"moma":18,"nat":"American","total":19},{"name":"Tapio Wirkkala","mplus":1,"moma":18,"nat":"Finnish","total":19},{"name":"Mako Idemitsu","mplus":4,"moma":14,"nat":"Japanese","total":18},{"name":"Hong Hao","mplus":12,"moma":6,"nat":"Chinese","total":18},{"name":"Cai Guo-Qiang","mplus":9,"moma":8,"nat":"Chinese","total":17},{"name":"Xu Bing","mplus":2,"moma":15,"nat":"Chinese","total":17},{"name":"Zhang Peili","mplus":13,"moma":4,"nat":"Chinese","total":17},{"name":"Nathalie Du Pasquier","mplus":8,"moma":9,"nat":"French","total":17},{"name":"Charlotte Moorman","mplus":11,"moma":5,"nat":"American","total":16},{"name":"Qiu Anxiong","mplus":2,"moma":14,"nat":"Chinese","total":16},{"name":"Huang Yan","mplus":8,"moma":8,"nat":"Chinese","total":16},{"name":"Eikoh Hosoe","mplus":3,"moma":13,"nat":"Japanese","total":16},{"name":"Michael Young","mplus":14,"moma":1,"nat":"British","total":15},{"name":"Charles Henri Ford","mplus":1,"moma":14,"nat":"American","total":15},{"name":"Xu Zhen","mplus":12,"moma":2,"nat":"Chinese","total":14},{"name":"Charles Atlas","mplus":5,"moma":9,"nat":"American","total":14},{"name":"Huang Yong Ping","mplus":11,"moma":3,"nat":"French","total":14},{"name":"Alfredo Jaar","mplus":6,"moma":8,"nat":"Chilean","total":14},{"name":"Ana Mendieta","mplus":4,"moma":10,"nat":"American","total":14},{"name":"Siah Armajani","mplus":3,"moma":11,"nat":"American","total":14},{"name":"Chen Shaoxiong","mplus":12,"moma":1,"nat":"Chinese","total":13},{"name":"Dara Birnbaum","mplus":5,"moma":8,"nat":"American","total":13},{"name":"Nadia Kaabi-Linke","mplus":1,"moma":12,"nat":"Tunisian","total":13},{"name":"Patty Chang","mplus":11,"moma":2,"nat":"American","total":13},{"name":"Zhang Ke","mplus":1,"moma":12,"nat":"Chinese","total":13},{"name":"Tetsumi Kudo","mplus":2,"moma":11,"nat":"Japanese","total":13},{"name":"Andreas Gursky","mplus":1,"moma":12,"nat":"German","total":13},{"name":"Hai Bo","mplus":11,"moma":1,"nat":"Chinese","total":12},{"name":"Rasheed Araeen","mplus":11,"moma":1,"nat":"British","total":12},{"name":"Lee Kit","mplus":10,"moma":1,"nat":"Hong Kong","total":11},{"name":"Katsuhiro Yamaguchi","mplus":6,"moma":5,"nat":"Japanese","total":11},{"name":"Christian Jankowski","mplus":9,"moma":2,"nat":"German","total":11},{"name":"Julian Opie","mplus":1,"moma":10,"nat":"British","total":11},{"name":"Sarah Sze","mplus":2,"moma":9,"nat":"American","total":11},{"name":"Peter Moore","mplus":4,"moma":6,"nat":"American","total":10},{"name":"Takashi Murakami","mplus":1,"moma":9,"nat":"Japanese","total":10},{"name":"Anwar Jalal Shemza","mplus":9,"moma":1,"nat":"British","total":10},{"name":"Ron Arad","mplus":3,"moma":7,"nat":"Israeli","total":10},{"name":"Ken Lum","mplus":7,"moma":3,"nat":"Canadian","total":10},{"name":"Jean Prouv\u00e9","mplus":1,"moma":9,"nat":"French","total":10},{"name":"Weng Fen","mplus":8,"moma":2,"nat":"Chinese","total":10},{"name":"Wang Qingsong","mplus":7,"moma":2,"nat":"Chinese","total":9},{"name":"Andr\u00e9 Breton","mplus":4,"moma":5,"nat":"French","total":9},{"name":"Miao Xiaochun","mplus":8,"moma":1,"nat":"Chinese","total":9},{"name":"Feng Mengbo","mplus":8,"moma":1,"nat":"Chinese","total":9},{"name":"Danh Vo","mplus":4,"moma":5,"nat":"Danish","total":9},{"name":"Charlotte Perriand","mplus":6,"moma":2,"nat":"French","total":8},{"name":"Zhang Huan","mplus":4,"moma":4,"nat":"Chinese","total":8},{"name":"David Hare","mplus":1,"moma":7,"nat":"American","total":8},{"name":"Isamu Kenmochi","mplus":6,"moma":2,"nat":"Japanese","total":8},{"name":"Vivan Sundaram","mplus":6,"moma":2,"nat":"Indian","total":8},{"name":"Shirazeh Houshiary","mplus":2,"moma":6,"nat":"Iranian","total":8},{"name":"Cecil Beaton","mplus":4,"moma":4,"nat":"British","total":8},{"name":"Song Dong","mplus":6,"moma":2,"nat":"Chinese","total":8},{"name":"Chen Zhen","mplus":2,"moma":5,"nat":"French","total":7},{"name":"Jos\u00e9 Mar\u00eda Sicilia","mplus":1,"moma":6,"nat":"Spanish","total":7},{"name":"Lee Ufan","mplus":3,"moma":4,"nat":"South Korean","total":7},{"name":"Martin Wong","mplus":1,"moma":6,"nat":"American","total":7},{"name":"Lu Chunsheng","mplus":6,"moma":1,"nat":"Chinese","total":7},{"name":"Kazuko Miyamoto","mplus":5,"moma":2,"nat":"American","total":7},{"name":"Aldo Rossi","mplus":1,"moma":6,"nat":"Italian","total":7},{"name":"Alessandro Mendini","mplus":1,"moma":6,"nat":"Italian","total":7},{"name":"Lin Tianmiao","mplus":3,"moma":4,"nat":"Chinese","total":7},{"name":"Cao Fei","mplus":4,"moma":3,"nat":"Chinese","total":7},{"name":"Wang Jianwei","mplus":4,"moma":2,"nat":"Chinese","total":6},{"name":"Do Ho Suh","mplus":1,"moma":5,"nat":"South Korean","total":6},{"name":"Walter Gropius","mplus":2,"moma":4,"nat":"German","total":6},{"name":"Oscar Niemeyer","mplus":1,"moma":5,"nat":"Brazilian","total":6},{"name":"Iwao Yamawaki","mplus":1,"moma":5,"nat":"Japanese","total":6},{"name":"Hong Lei","mplus":3,"moma":3,"nat":"Chinese","total":6},{"name":"Marcel Wanders","mplus":5,"moma":1,"nat":"Dutch","total":6},{"name":"Iwan Baan","mplus":2,"moma":4,"nat":"Dutch","total":6},{"name":"Yang Fudong","mplus":4,"moma":2,"nat":"Chinese","total":6},{"name":"Paul Pfeiffer","mplus":2,"moma":3,"nat":"American","total":5},{"name":"Ian Cheng","mplus":1,"moma":4,"nat":"American","total":5},{"name":"Isaac Julien","mplus":1,"moma":4,"nat":"British","total":5},{"name":"Yang Zhenzhong","mplus":3,"moma":2,"nat":"Chinese","total":5},{"name":"Ming Wong","mplus":4,"moma":1,"nat":"Singaporean","total":5},{"name":"Martine Bedin","mplus":4,"moma":1,"nat":"French","total":5},{"name":"Etel Adnan","mplus":3,"moma":2,"nat":"American","total":5},{"name":"Li Yongbin","mplus":3,"moma":2,"nat":"Chinese","total":5},{"name":"Jasper Morrison","mplus":1,"moma":3,"nat":"British","total":4},{"name":"Yau Ching","mplus":3,"moma":1,"nat":"Hong Kong","total":4},{"name":"Phyllis Baldino","mplus":3,"moma":1,"nat":"American","total":4},{"name":"Barbara Buckner","mplus":3,"moma":1,"nat":"American","total":4},{"name":"Beatrice Wood","mplus":1,"moma":3,"nat":"American","total":4},{"name":"Wu Tsang","mplus":1,"moma":3,"nat":"American","total":4},{"name":"Lina Bo Bardi","mplus":1,"moma":3,"nat":"Brazilian","total":4},{"name":"Raymond Loewy","mplus":2,"moma":2,"nat":"American","total":4},{"name":"Steven Holl Architects","mplus":2,"moma":2,"nat":"American","total":4},{"name":"Li Ming","mplus":3,"moma":1,"nat":"Chinese","total":4},{"name":"Dominique Gonzalez-Foerster","mplus":1,"moma":3,"nat":"French","total":4},{"name":"Toyo Ito & Associates, Architects","mplus":1,"moma":2,"nat":"Japanese","total":3},{"name":"Li Binyuan","mplus":2,"moma":1,"nat":"Chinese","total":3},{"name":"Abraham Cruzvillegas","mplus":1,"moma":2,"nat":"Mexican","total":3},{"name":"Ha Chong-Hyun","mplus":2,"moma":1,"nat":"South Korean","total":3},{"name":"CAMP","mplus":2,"moma":1,"nat":"Indian","total":3},{"name":"Cui Jie","mplus":2,"moma":1,"nat":"Chinese","total":3},{"name":"Chung Chang-Sup","mplus":2,"moma":1,"nat":"South Korean","total":3},{"name":"Pacita Abad","mplus":2,"moma":1,"nat":"Filipino","total":3},{"name":"Liu Xiaodong","mplus":2,"moma":1,"nat":"Chinese","total":3},{"name":"John Gerrard","mplus":1,"moma":1,"nat":"Irish","total":2},{"name":"Tino Sehgal","mplus":1,"moma":1,"nat":"British","total":2},{"name":"Avery Singer","mplus":1,"moma":1,"nat":"American","total":2},{"name":"David Medalla","mplus":1,"moma":1,"nat":"Filipino","total":2},{"name":"Tom Dixon","mplus":1,"moma":1,"nat":"British","total":2},{"name":"Yuya Ushida","mplus":1,"moma":1,"nat":"Japanese","total":2},{"name":"Satyendra Pakhal\u00e9","mplus":1,"moma":1,"nat":"Indian","total":2},{"name":"Choi Byung Hoon","mplus":1,"moma":1,"nat":"South Korean","total":2},{"name":"Tomie Ohtake","mplus":1,"moma":1,"nat":"Brazilian","total":2},{"name":"Michele De Lucchi","mplus":1,"moma":1,"nat":"Italian","total":2},{"name":"Victor Obsatz","mplus":1,"moma":1,"nat":"American","total":2},{"name":"Michael Joo","mplus":1,"moma":1,"nat":"American","total":2},{"name":"James Dyson","mplus":1,"moma":1,"nat":"British","total":2},{"name":"Nicolas Party","mplus":1,"moma":1,"nat":"Swiss","total":2},{"name":"Katherine S. Dreier","mplus":1,"moma":1,"nat":"American","total":2},{"name":"Wang Jinsong","mplus":1,"moma":1,"nat":"Chinese","total":2},{"name":"Aernout Mik","mplus":1,"moma":1,"nat":"Dutch","total":2},{"name":"Pinaree Sanpitak","mplus":1,"moma":1,"nat":"Thai","total":2},{"name":"Christian Zervos","mplus":1,"moma":1,"nat":"French","total":2},{"name":"OPEN Architecture","mplus":1,"moma":1,"nat":"Chinese-American","total":2},{"name":"Arturo Schwarz","mplus":1,"moma":1,"nat":"Italian","total":2},{"name":"Eric Baudelaire","mplus":1,"moma":1,"nat":"French","total":2},{"name":"Kishio Suga","mplus":1,"moma":1,"nat":"Japanese","total":2},{"name":"Yasumasa Morimura","mplus":1,"moma":1,"nat":"Japanese","total":2},{"name":"Meiro Koizumi","mplus":1,"moma":1,"nat":"Japanese","total":2},{"name":"Candice Breitz","mplus":1,"moma":1,"nat":"South African","total":2},{"name":"Park Hyunki","mplus":1,"moma":1,"nat":"South Korean","total":2},{"name":"Park Seo-Bo","mplus":1,"moma":1,"nat":"South Korean","total":2},{"name":"Amar Kanwar","mplus":1,"moma":1,"nat":"Research Needed","total":2}]}